Metadata-Version: 1.0
Name: probabilitydc-distributions
Version: 0.1
Summary: Probability discrete continous distributions
Home-page: UNKNOWN
Author: Harsha S
Author-email: UNKNOWN
License: UNKNOWN
Platform: UNKNOWN
